table_schema_to_markdown/__init__.py
table_schema_to_markdown-0.4.13.data/scripts/table-schema-to-md
table_schema_to_markdown-0.4.13.dist-info/LICENSE
table_schema_to_markdown-0.4.13.dist-info/METADATA
table_schema_to_markdown-0.4.13.dist-info/WHEEL
table_schema_to_markdown-0.4.13.dist-info/top_level.txt
table_schema_to_markdown-0.4.13.dist-info/RECORD
