Metadata-Version: 2.1
Name: table-schema-to-markdown
Version: 0.4.13
Summary: Generate Markdown documentation from a table schema file from Frictionless Data
Home-page: https://github.com/geoffreyaldebert/table-schema-to-markdown
Author: Antoine Augusti, Geoffrey Aldebert
Author-email: hi@antoine-augusti.fr, geoffrey.aldebert@data.gouv.fr
License: MIT
Keywords: frictionlessdata,documentation,tableschema,table-schema,frictionless data,open data,json schema,json table schema,data package,tabular data package
Platform: UNKNOWN
Classifier: Development Status :: 3 - Alpha
Classifier: Intended Audience :: Developers
Classifier: License :: OSI Approved :: MIT License
Classifier: Operating System :: OS Independent
Classifier: Programming Language :: Python :: 3
Classifier: Programming Language :: Python :: 3.4
Classifier: Programming Language :: Python :: 3.5
Classifier: Programming Language :: Python :: 3.6
Classifier: Topic :: Software Development :: Libraries :: Python Modules
Requires-Python: >=3, <4
Provides-Extra: dev
Requires-Dist: nose ; extra == 'dev'
